delay/delay_line.v
module delay_line (
	input wire clk,
	input wire rst,
        input wire [4:0] delay,
	input wire [18:0] pcm_data,
	output wire [18:0] delayed_pcm_data
);

parameter MAX_DELAY = 32;
integer i, counter = 0;
reg [18:0] buffer [MAX_DELAY:0];

always @(posedge clk or posedge rst) begin
	if (rst) begin
		counter <= 0;
		for (i = 0; i <= MAX_DELAY; i = i + 1) begin
			buffer[i] <= 0;
		end
	end else begin
		buffer[counter] <= pcm_data;
		counter <= (counter + 1) % ({27'b0, delay} + 1);
	end
end

assign delayed_pcm_data = buffer[(counter + 1) % ({27'b0, delay} + 1)];

endmodule

delay/delay_module.v
module delay_module (
  input wire clk,
  input wire rst,
  input wire [4:0] delay_select,
  input wire [18:0] pcm_data_0,
  input wire [18:0] pcm_data_1,
  input wire [18:0] pcm_data_2,
  input wire [18:0] pcm_data_3,
  input wire [18:0] pcm_data_4,
  input wire [18:0] pcm_data_5,
  input wire [18:0] pcm_data_6,
  input wire [18:0] pcm_data_7,
  input wire [18:0] pcm_data_8,
  input wire [18:0] pcm_data_9,
  input wire [18:0] pcm_data_10,
  input wire [18:0] pcm_data_11,
  input wire [18:0] pcm_data_12,
  input wire [18:0] pcm_data_13,
  input wire [18:0] pcm_data_14,
  input wire [18:0] pcm_data_15,
  output wire [18:0] delayed_pcm_data_0,
  output wire [18:0] delayed_pcm_data_1,
  output wire [18:0] delayed_pcm_data_2,
  output wire [18:0] delayed_pcm_data_3,
  output wire [18:0] delayed_pcm_data_4,
  output wire [18:0] delayed_pcm_data_5,
  output wire [18:0] delayed_pcm_data_6,
  output wire [18:0] delayed_pcm_data_7,
  output wire [18:0] delayed_pcm_data_8,
  output wire [18:0] delayed_pcm_data_9,
  output wire [18:0] delayed_pcm_data_10,
  output wire [18:0] delayed_pcm_data_11,
  output wire [18:0] delayed_pcm_data_12,
  output wire [18:0] delayed_pcm_data_13,
  output wire [18:0] delayed_pcm_data_14,
  output wire [18:0] delayed_pcm_data_15
);

    wire [18:0] pcm_data [15:0];
    wire [18:0] delayed_pcm_data [15:0];
    reg [4:0] mic_delays [15:0];  

    integer x;
    initial begin
      for (x = 0; x < 16; x = x + 1) begin
        mic_delays[x] = 0;
       end
    end

    assign pcm_data[0] = pcm_data_0;
    assign pcm_data[1] = pcm_data_1;
    assign pcm_data[2] = pcm_data_2;
    assign pcm_data[3] = pcm_data_3;
    assign pcm_data[4] = pcm_data_4;
    assign pcm_data[5] = pcm_data_5;
    assign pcm_data[6] = pcm_data_6;
    assign pcm_data[7] = pcm_data_7;
    assign pcm_data[8] = pcm_data_8;
    assign pcm_data[9] = pcm_data_9;
    assign pcm_data[10] = pcm_data_10;
    assign pcm_data[11] = pcm_data_11;
    assign pcm_data[12] = pcm_data_12;
    assign pcm_data[13] = pcm_data_13;
    assign pcm_data[14] = pcm_data_14;
    assign pcm_data[15] = pcm_data_15;

    assign delayed_pcm_data_0 = delayed_pcm_data[0];
    assign delayed_pcm_data_1 = delayed_pcm_data[1];
    assign delayed_pcm_data_2 = delayed_pcm_data[2];
    assign delayed_pcm_data_3 = delayed_pcm_data[3];
    assign delayed_pcm_data_4 = delayed_pcm_data[4];
    assign delayed_pcm_data_5 = delayed_pcm_data[5];
    assign delayed_pcm_data_6 = delayed_pcm_data[6];
    assign delayed_pcm_data_7 = delayed_pcm_data[7];
    assign delayed_pcm_data_8 = delayed_pcm_data[8];
    assign delayed_pcm_data_9 = delayed_pcm_data[9];
    assign delayed_pcm_data_10 = delayed_pcm_data[10];
    assign delayed_pcm_data_11 = delayed_pcm_data[11];
    assign delayed_pcm_data_12 = delayed_pcm_data[12];
    assign delayed_pcm_data_13 = delayed_pcm_data[13];
    assign delayed_pcm_data_14 = delayed_pcm_data[14];
    assign delayed_pcm_data_15 = delayed_pcm_data[15];

    always @(delay_select) begin
        case (delay_select)
	  0: begin
                mic_delays[0] = 0;
                mic_delays[1] = 4;
                mic_delays[2] = 10;
                mic_delays[3] = 12;
                mic_delays[4] = 14;
                mic_delays[5] = 18;
                mic_delays[6] = 0;
                mic_delays[7] = 0;
                mic_delays[8] = 0;
                mic_delays[9] = 0;
                mic_delays[10] = 0;
                mic_delays[11] = 4;
                mic_delays[12] = 10;
                mic_delays[13] = 12;
                mic_delays[14] = 14;
                mic_delays[15] = 18;
            end
    endcase
    end

    genvar i;

    generate
      for (i = 0; i < 16; i = i + 1) begin : delay_line_gen
      delay_line u_delay_line (
        .clk(clk),
        .rst(rst),
        .delay(mic_delays[i]),
        .pcm_data(pcm_data[i]),
        .delayed_pcm_data(delayed_pcm_data[i])
      );
      end
    endgenerate

endmodule

delay/tb_delay_line.v
`timescale 1ns / 1ns

module tb_delay_line;

  parameter DELAY = 50;
  
  reg clk;
  reg rst;
  reg [4:0] delay_select;
  reg [18:0] cic_data [15:0];
  wire [18:0] delayed_data [15:0];

  delay_module u_delay_module (
            .clk(clk),
            .rst(rst),
            .delay_select(delay_select),
            .pcm_data_0(cic_data[0]),
            .pcm_data_1(cic_data[8]),
            .pcm_data_2(cic_data[1]),
            .pcm_data_3(cic_data[9]),
            .pcm_data_4(cic_data[2]),
            .pcm_data_5(cic_data[10]),
            .pcm_data_6(cic_data[3]),
            .pcm_data_7(cic_data[11]),
            .pcm_data_8(cic_data[4]),
            .pcm_data_9(cic_data[12]),
            .pcm_data_10(cic_data[5]),
            .pcm_data_11(cic_data[13]),
            .pcm_data_12(cic_data[6]),
            .pcm_data_13(cic_data[14]),
            .pcm_data_14(cic_data[7]),
            .pcm_data_15(cic_data[15]),
            .delayed_pcm_data_0(delayed_data[0]),
            .delayed_pcm_data_1(delayed_data[1]),
            .delayed_pcm_data_2(delayed_data[2]),
            .delayed_pcm_data_3(delayed_data[3]),
            .delayed_pcm_data_4(delayed_data[4]),
            .delayed_pcm_data_5(delayed_data[5]),
            .delayed_pcm_data_6(delayed_data[6]),
            .delayed_pcm_data_7(delayed_data[7]),
            .delayed_pcm_data_8(delayed_data[8]),
            .delayed_pcm_data_9(delayed_data[9]),
            .delayed_pcm_data_10(delayed_data[10]),
            .delayed_pcm_data_11(delayed_data[11]),
            .delayed_pcm_data_12(delayed_data[12]),
            .delayed_pcm_data_13(delayed_data[13]),
            .delayed_pcm_data_14(delayed_data[14]),
            .delayed_pcm_data_15(delayed_data[15])
        );

  
  initial clk = 1;
  always #10 clk = ~clk;  // 20ns clock period (50MHz clock)
  
  integer i;

  initial begin
  $dumpfile("tb_delay_line.vcd");
  $dumpvars(0,tb_delay_line);

  rst = 0;
  
  delay_select <= 0;
      
  for (i = 0; i < 16; i = i + 1) begin
    cic_data[i] <= 0;
  end

  // Apply test vector
  for (i = 0; i < 16; i = i + 1) begin
    cic_data[i] <= 1;
  end    
  #30
  for (i = 0; i < 16; i = i + 1) begin
    cic_data[i] <= 2;
  end
  #30
for (i = 0; i < 16; i = i + 1) begin
    cic_data[i] <= 3;
  end
  #30
for (i = 0; i < 16; i = i + 1) begin
    cic_data[i] <= 4;
  end
  #30
for (i = 0; i < 16; i = i + 1) begin
    cic_data[i] <= 5;
  end

  $monitor("At time %t, delayed_pcm_data = %h %h %h %h %h %h %h %h %h %h %h %h %h %h %h %h", $time, 
delayed_data[0], delayed_data[1],  delayed_data[2],  delayed_data[3], delayed_data[4], 
delayed_data[5],  delayed_data[6],  delayed_data[7], 
delayed_data[8], delayed_data[9],  delayed_data[10],  delayed_data[11], delayed_data[12],                                 
delayed_data[13],  delayed_data[14],  delayed_data[15],);
  #5000

  $finish;
  end
  
endmodule

delay/tb_delay_line.vcd
$date
	Wed Jul 31 18:40:28 2024
$end
$version
	Icarus Verilog
$end
$timescale
	1ns
$end
$scope module tb_delay_line $end
$var reg 1 ! clk $end
$var reg 5 " delay_select [4:0] $end
$var reg 1 # rst $end
$var integer 32 $ i [31:0] $end
$scope module u_delay_module $end
$var wire 1 ! clk $end
$var wire 5 % delay_select [4:0] $end
$var wire 19 & delayed_pcm_data_0 [18:0] $end
$var wire 19 ' delayed_pcm_data_1 [18:0] $end
$var wire 19 ( delayed_pcm_data_10 [18:0] $end
$var wire 19 ) delayed_pcm_data_11 [18:0] $end
$var wire 19 * delayed_pcm_data_12 [18:0] $end
$var wire 19 + delayed_pcm_data_13 [18:0] $end
$var wire 19 , delayed_pcm_data_14 [18:0] $end
$var wire 19 - delayed_pcm_data_15 [18:0] $end
$var wire 19 . delayed_pcm_data_2 [18:0] $end
$var wire 19 / delayed_pcm_data_3 [18:0] $end
$var wire 19 0 delayed_pcm_data_4 [18:0] $end
$var wire 19 1 delayed_pcm_data_5 [18:0] $end
$var wire 19 2 delayed_pcm_data_6 [18:0] $end
$var wire 19 3 delayed_pcm_data_7 [18:0] $end
$var wire 19 4 delayed_pcm_data_8 [18:0] $end
$var wire 19 5 delayed_pcm_data_9 [18:0] $end
$var wire 19 6 pcm_data_0 [18:0] $end
$var wire 19 7 pcm_data_1 [18:0] $end
$var wire 19 8 pcm_data_10 [18:0] $end
$var wire 19 9 pcm_data_11 [18:0] $end
$var wire 19 : pcm_data_12 [18:0] $end
$var wire 19 ; pcm_data_13 [18:0] $end
$var wire 19 < pcm_data_14 [18:0] $end
$var wire 19 = pcm_data_15 [18:0] $end
$var wire 19 > pcm_data_2 [18:0] $end
$var wire 19 ? pcm_data_3 [18:0] $end
$var wire 19 @ pcm_data_4 [18:0] $end
$var wire 19 A pcm_data_5 [18:0] $end
$var wire 19 B pcm_data_6 [18:0] $end
$var wire 19 C pcm_data_7 [18:0] $end
$var wire 19 D pcm_data_8 [18:0] $end
$var wire 19 E pcm_data_9 [18:0] $end
$var wire 1 # rst $end
$var integer 32 F x [31:0] $end
$scope begin delay_line_gen[0] $end
$scope module u_delay_line $end
$var wire 1 ! clk $end
$var wire 5 G delay [4:0] $end
$var wire 19 H delayed_pcm_data [18:0] $end
$var wire 19 I pcm_data [18:0] $end
$var wire 1 # rst $end
$var integer 32 J counter [31:0] $end
$var integer 32 K i [31:0] $end
$upscope $end
$upscope $end
$scope begin delay_line_gen[1] $end
$scope module u_delay_line $end
$var wire 1 ! clk $end
$var wire 5 L delay [4:0] $end
$var wire 19 M delayed_pcm_data [18:0] $end
$var wire 19 N pcm_data [18:0] $end
$var wire 1 # rst $end
$var integer 32 O counter [31:0] $end
$var integer 32 P i [31:0] $end
$upscope $end
$upscope $end
$scope begin delay_line_gen[2] $end
$scope module u_delay_line $end
$var wire 1 ! clk $end
$var wire 5 Q delay [4:0] $end
$var wire 19 R delayed_pcm_data [18:0] $end
$var wire 19 S pcm_data [18:0] $end
$var wire 1 # rst $end
$var integer 32 T counter [31:0] $end
$var integer 32 U i [31:0] $end
$upscope $end
$upscope $end
$scope begin delay_line_gen[3] $end
$scope module u_delay_line $end
$var wire 1 ! clk $end
$var wire 5 V delay [4:0] $end
$var wire 19 W delayed_pcm_data [18:0] $end
$var wire 19 X pcm_data [18:0] $end
$var wire 1 # rst $end
$var integer 32 Y counter [31:0] $end
$var integer 32 Z i [31:0] $end
$upscope $end
$upscope $end
$scope begin delay_line_gen[4] $end
$scope module u_delay_line $end
$var wire 1 ! clk $end
$var wire 5 [ delay [4:0] $end
$var wire 19 \ delayed_pcm_data [18:0] $end
$var wire 19 ] pcm_data [18:0] $end
$var wire 1 # rst $end
$var integer 32 ^ counter [31:0] $end
$var integer 32 _ i [31:0] $end
$upscope $end
$upscope $end
$scope begin delay_line_gen[5] $end
$scope module u_delay_line $end
$var wire 1 ! clk $end
$var wire 5 ` delay [4:0] $end
$var wire 19 a delayed_pcm_data [18:0] $end
$var wire 19 b pcm_data [18:0] $end
$var wire 1 # rst $end
$var integer 32 c counter [31:0] $end
$var integer 32 d i [31:0] $end
$upscope $end
$upscope $end
$scope begin delay_line_gen[6] $end
$scope module u_delay_line $end
$var wire 1 ! clk $end
$var wire 5 e delay [4:0] $end
$var wire 19 f delayed_pcm_data [18:0] $end
$var wire 19 g pcm_data [18:0] $end
$var wire 1 # rst $end
$var integer 32 h counter [31:0] $end
$var integer 32 i i [31:0] $end
$upscope $end
$upscope $end
$scope begin delay_line_gen[7] $end
$scope module u_delay_line $end
$var wire 1 ! clk $end
$var wire 5 j delay [4:0] $end
$var wire 19 k delayed_pcm_data [18:0] $end
$var wire 19 l pcm_data [18:0] $end
$var wire 1 # rst $end
$var integer 32 m counter [31:0] $end
$var integer 32 n i [31:0] $end
$upscope $end
$upscope $end
$scope begin delay_line_gen[8] $end
$scope module u_delay_line $end
$var wire 1 ! clk $end
$var wire 5 o delay [4:0] $end
$var wire 19 p delayed_pcm_data [18:0] $end
$var wire 19 q pcm_data [18:0] $end
$var wire 1 # rst $end
$var integer 32 r counter [31:0] $end
$var integer 32 s i [31:0] $end
$upscope $end
$upscope $end
$scope begin delay_line_gen[9] $end
$scope module u_delay_line $end
$var wire 1 ! clk $end
$var wire 5 t delay [4:0] $end
$var wire 19 u delayed_pcm_data [18:0] $end
$var wire 19 v pcm_data [18:0] $end
$var wire 1 # rst $end
$var integer 32 w counter [31:0] $end
$var integer 32 x i [31:0] $end
$upscope $end
$upscope $end
$scope begin delay_line_gen[10] $end
$scope module u_delay_line $end
$var wire 1 ! clk $end
$var wire 5 y delay [4:0] $end
$var wire 19 z delayed_pcm_data [18:0] $end
$var wire 19 { pcm_data [18:0] $end
$var wire 1 # rst $end
$var integer 32 | counter [31:0] $end
$var integer 32 } i [31:0] $end
$upscope $end
$upscope $end
$scope begin delay_line_gen[11] $end
$scope module u_delay_line $end
$var wire 1 ! clk $end
$var wire 5 ~ delay [4:0] $end
$var wire 19 !" delayed_pcm_data [18:0] $end
$var wire 19 "" pcm_data [18:0] $end
$var wire 1 # rst $end
$var integer 32 #" counter [31:0] $end
$var integer 32 $" i [31:0] $end
$upscope $end
$upscope $end
$scope begin delay_line_gen[12] $end
$scope module u_delay_line $end
$var wire 1 ! clk $end
$var wire 5 %" delay [4:0] $end
$var wire 19 &" delayed_pcm_data [18:0] $end
$var wire 19 '" pcm_data [18:0] $end
$var wire 1 # rst $end
$var integer 32 (" counter [31:0] $end
$var integer 32 )" i [31:0] $end
$upscope $end
$upscope $end
$scope begin delay_line_gen[13] $end
$scope module u_delay_line $end
$var wire 1 ! clk $end
$var wire 5 *" delay [4:0] $end
$var wire 19 +" delayed_pcm_data [18:0] $end
$var wire 19 ," pcm_data [18:0] $end
$var wire 1 # rst $end
$var integer 32 -" counter [31:0] $end
$var integer 32 ." i [31:0] $end
$upscope $end
$upscope $end
$scope begin delay_line_gen[14] $end
$scope module u_delay_line $end
$var wire 1 ! clk $end
$var wire 5 /" delay [4:0] $end
$var wire 19 0" delayed_pcm_data [18:0] $end
$var wire 19 1" pcm_data [18:0] $end
$var wire 1 # rst $end
$var integer 32 2" counter [31:0] $end
$var integer 32 3" i [31:0] $end
$upscope $end
$upscope $end
$scope begin delay_line_gen[15] $end
$scope module u_delay_line $end
$var wire 1 ! clk $end
$var wire 5 4" delay [4:0] $end
$var wire 19 5" delayed_pcm_data [18:0] $end
$var wire 19 6" pcm_data [18:0] $end
$var wire 1 # rst $end
$var integer 32 7" counter [31:0] $end
$var integer 32 8" i [31:0] $end
$upscope $end
$upscope $end
$upscope $end
$upscope $end
$enddefinitions $end
#0
$dumpvars
bx 8"
b0 7"
b1 6"
bx 5"
b10010 4"
bx 3"
b0 2"
b1 1"
bx 0"
b1110 /"
bx ."
b0 -"
b1 ,"
bx +"
b1100 *"
bx )"
b0 ("
b1 '"
bx &"
b1010 %"
bx $"
b0 #"
b1 ""
bx !"
b100 ~
bx }
b0 |
b1 {
bx z
b0 y
bx x
b0 w
b1 v
bx u
b0 t
bx s
b0 r
b1 q
bx p
b0 o
bx n
b0 m
b1 l
bx k
b0 j
bx i
b0 h
b1 g
bx f
b0 e
bx d
b0 c
b1 b
bx a
b10010 `
bx _
b0 ^
b1 ]
bx \
b1110 [
bx Z
b0 Y
b1 X
bx W
b1100 V
bx U
b0 T
b1 S
bx R
b1010 Q
bx P
b0 O
b1 N
bx M
b100 L
bx K
b0 J
b1 I
bx H
b0 G
b10000 F
b1 E
b1 D
b1 C
b1 B
b1 A
b1 @
b1 ?
b1 >
b1 =
b1 <
b1 ;
b1 :
b1 9
b1 8
b1 7
b1 6
bx 5
bx 4
bx 3
bx 2
bx 1
bx 0
bx /
bx .
bx -
bx ,
bx +
bx *
bx )
bx (
bx '
bx &
b0 %
b10000 $
0#
b0 "
1!
$end
#10
0!
#20
b1 7"
b1 2"
b1 -"
b1 ("
b1 #"
b1 (
b1 z
b1 5
b1 u
b1 4
b1 p
b1 3
b1 k
b1 2
b1 f
b1 c
b1 ^
b1 Y
b1 T
b1 O
b1 &
b1 H
1!
#30
b10 6"
b10 =
b10 ,"
b10 ;
b10 ""
b10 9
b10 v
b10 E
b10 l
b10 C
b10 b
b10 A
b10 X
b10 ?
b10 N
b10 7
b10 1"
b10 <
b10 '"
b10 :
b10 {
b10 8
b10 q
b10 D
b10 g
b10 B
b10 ]
b10 @
b10 S
b10 >
b10 I
b10 6
0!
b10000 $
#40
b10 &
b10 H
b10 O
b10 T
b10 Y
b10 ^
b10 c
b10 2
b10 f
b10 3
b10 k
b10 4
b10 p
b10 5
b10 u
b10 (
b10 z
b10 #"
b10 ("
b10 -"
b10 2"
b10 7"
1!
#50
0!
#60
b11 7"
b11 2"
b11 -"
b11 ("
b11 #"
b11 c
b11 ^
b11 Y
b11 T
b11 O
b11 6"
b11 =
b11 ,"
b11 ;
b11 ""
b11 9
b11 v
b11 E
b11 l
b11 C
b11 b
b11 A
b11 X
b11 ?
b11 N
b11 7
b11 1"
b11 <
b11 '"
b11 :
b11 {
b11 8
b11 q
b11 D
b11 g
b11 B
b11 ]
b11 @
b11 S
b11 >
b11 I
b11 6
1!
b10000 $
#70
0!
#80
b11 &
b11 H
b1 '
b1 M
b100 O
b100 T
b100 Y
b100 ^
b100 c
b11 2
b11 f
b11 3
b11 k
b11 4
b11 p
b11 5
b11 u
b11 (
b11 z
b1 )
b1 !"
b100 #"
b100 ("
b100 -"
b100 2"
b100 7"
1!
#90
b100 6"
b100 =
b100 ,"
b100 ;
b100 ""
b100 9
b100 v
b100 E
b100 l
b100 C
b100 b
b100 A
b100 X
b100 ?
b100 N
b100 7
b100 1"
b100 <
b100 '"
b100 :
b100 {
b100 8
b100 q
b100 D
b100 g
b100 B
b100 ]
b100 @
b100 S
b100 >
b100 I
b100 6
0!
b10000 $
#100
b101 7"
b101 2"
b101 -"
b101 ("
b10 )
b10 !"
b0 #"
b100 (
b100 z
b100 5
b100 u
b100 4
b100 p
b100 3
b100 k
b100 2
b100 f
b101 c
b101 ^
b101 Y
b101 T
b10 '
b10 M
b0 O
b100 &
b100 H
1!
#110
0!
#120
b1 O
b110 T
b110 Y
b110 ^
b110 c
b1 #"
b110 ("
b110 -"
b110 2"
b110 7"
b101 6"
b101 =
b101 ,"
b101 ;
b101 ""
b101 9
b101 v
b101 E
b101 l
b101 C
b101 b
b101 A
b101 X
b101 ?
b101 N
b101 7
b101 1"
b101 <
b101 '"
b101 :
b101 {
b101 8
b101 q
b101 D
b101 g
b101 B
b101 ]
b101 @
b101 S
b101 >
b101 I
b101 6
1!
b10000 $
#130
0!
#140
b111 7"
b111 2"
b111 -"
b111 ("
b11 )
b11 !"
b10 #"
b101 (
b101 z
b101 5
b101 u
b101 4
b101 p
b101 3
b101 k
b101 2
b101 f
b111 c
b111 ^
b111 Y
b111 T
b11 '
b11 M
b10 O
b101 &
b101 H
1!
#150
0!
#160
b100 '
b100 M
b11 O
b1000 T
b1000 Y
b1000 ^
b1000 c
b100 )
b100 !"
b11 #"
b1000 ("
b1000 -"
b1000 2"
b1000 7"
1!
#170
0!
#180
b1001 7"
b1001 2"
b1001 -"
b1001 ("
b100 #"
b1001 c
b1001 ^
b1001 Y
b1001 T
b100 O
1!
#190
0!
#200
b101 '
b101 M
b0 O
b1 .
b1 R
b1010 T
b1010 Y
b1010 ^
b1010 c
b101 )
b101 !"
b0 #"
b1 *
b1 &"
b1010 ("
b1010 -"
b1010 2"
b1010 7"
1!
#210
0!
#220
b1011 7"
b1011 2"
b1011 -"
b10 *
b10 &"
b0 ("
b1 #"
b1011 c
b1011 ^
b1011 Y
b10 .
b10 R
b0 T
b1 O
1!
#230
0!
#240
b10 O
b1 T
b1 /
b1 W
b1100 Y
b1100 ^
b1100 c
b10 #"
b1 ("
b1 +
b1 +"
b1100 -"
b1100 2"
b1100 7"
1!
#250
0!
#260
b1101 7"
b1101 2"
b10 +
b10 +"
b0 -"
b11 *
b11 &"
b10 ("
b11 #"
b1101 c
b1101 ^
b10 /
b10 W
b0 Y
b11 .
b11 R
b10 T
b11 O
1!
#270
0!
#280
b100 O
b100 .
b100 R
b11 T
b1 Y
b1 0
b1 \
b1110 ^
b1110 c
b100 #"
b100 *
b100 &"
b11 ("
b1 -"
b1 ,
b1 0"
b1110 2"
b1110 7"
1!
#290
0!
#300
b1111 7"
b10 ,
b10 0"
b0 2"
b11 +
b11 +"
b10 -"
b100 ("
b0 #"
b1111 c
b10 0
b10 \
b0 ^
b11 /
b11 W
b10 Y
b100 T
b0 O
1!
#310
0!
#320
b1 O
b101 .
b101 R
b101 T
b100 /
b100 W
b11 Y
b1 ^
b10000 c
b1 #"
b101 *
b101 &"
b101 ("
b100 +
b100 +"
b11 -"
b1 2"
b10000 7"
1!
#330
0!
#340
b10001 7"
b11 ,
b11 0"
b10 2"
b100 -"
b110 ("
b10 #"
b10001 c
b11 0
b11 \
b10 ^
b100 Y
b110 T
b10 O
1!
#350
0!
#360
b11 O
b111 T
b101 /
b101 W
b101 Y
b100 0
b100 \
b11 ^
b1 1
b1 a
b10010 c
b11 #"
b111 ("
b101 +
b101 +"
b101 -"
b100 ,
b100 0"
b11 2"
b1 -
b1 5"
b10010 7"
1!
#370
0!
#380
b10 -
b10 5"
b0 7"
b100 2"
b110 -"
b1000 ("
b100 #"
b10 1
b10 a
b0 c
b100 ^
b110 Y
b1000 T
b100 O
1!
#390
0!
#400
b0 O
b1001 T
b111 Y
b101 0
b101 \
b101 ^
b1 c
b0 #"
b1001 ("
b111 -"
b101 ,
b101 0"
b101 2"
b1 7"
1!
#410
0!
#420
b11 -
b11 5"
b10 7"
b110 2"
b1000 -"
b1010 ("
b1 #"
b11 1
b11 a
b10 c
b110 ^
b1000 Y
b1010 T
b1 O
1!
#430
0!
#440
b10 O
b0 T
b1001 Y
b111 ^
b100 1
b100 a
b11 c
b10 #"
b0 ("
b1001 -"
b111 2"
b100 -
b100 5"
b11 7"
1!
#450
0!
#460
b100 7"
b1000 2"
b1010 -"
b1 ("
b11 #"
b100 c
b1000 ^
b1010 Y
b1 T
b11 O
1!
#470
0!
#480
b100 O
b10 T
b1011 Y
b1001 ^
b101 1
b101 a
b101 c
b100 #"
b10 ("
b1011 -"
b1001 2"
b101 -
b101 5"
b101 7"
1!
#490
0!
#500
b110 7"
b1010 2"
b1100 -"
b11 ("
b0 #"
b110 c
b1010 ^
b1100 Y
b11 T
b0 O
1!
#510
0!
#520
b1 O
b100 T
b0 Y
b1011 ^
b111 c
b1 #"
b100 ("
b0 -"
b1011 2"
b111 7"
1!
#530
0!
#540
b1000 7"
b1100 2"
b1 -"
b101 ("
b10 #"
b1000 c
b1100 ^
b1 Y
b101 T
b10 O
1!
#550
0!
#560
b11 O
b110 T
b10 Y
b1101 ^
b1001 c
b11 #"
b110 ("
b10 -"
b1101 2"
b1001 7"
1!
#570
0!
#580
b1010 7"
b1110 2"
b11 -"
b111 ("
b100 #"
b1010 c
b1110 ^
b11 Y
b111 T
b100 O
1!
#590
0!
#600
b0 O
b1000 T
b100 Y
b0 ^
b1011 c
b0 #"
b1000 ("
b100 -"
b0 2"
b1011 7"
1!
#610
0!
#620
b1100 7"
b1 2"
b101 -"
b1001 ("
b1 #"
b1100 c
b1 ^
b101 Y
b1001 T
b1 O
1!
#630
0!
#640
b10 O
b1010 T
b110 Y
b10 ^
b1101 c
b10 #"
b1010 ("
b110 -"
b10 2"
b1101 7"
1!
#650
0!
#660
b1110 7"
b11 2"
b111 -"
b0 ("
b11 #"
b1110 c
b11 ^
b111 Y
b0 T
b11 O
1!
#670
0!
#680
b100 O
b1 T
b1000 Y
b100 ^
b1111 c
b100 #"
b1 ("
b1000 -"
b100 2"
b1111 7"
1!
#690
0!
#700
b10000 7"
b101 2"
b1001 -"
b10 ("
b0 #"
b10000 c
b101 ^
b1001 Y
b10 T
b0 O
1!
#710
0!
#720
b1 O
b11 T
b1010 Y
b110 ^
b10001 c
b1 #"
b11 ("
b1010 -"
b110 2"
b10001 7"
1!
#730
0!
#740
b10010 7"
b111 2"
b1011 -"
b100 ("
b10 #"
b10010 c
b111 ^
b1011 Y
b100 T
b10 O
1!
#750
0!
#760
b11 O
b101 T
b1100 Y
b1000 ^
b0 c
b11 #"
b101 ("
b1100 -"
b1000 2"
b0 7"
1!
#770
0!
#780
b1 7"
b1001 2"
b0 -"
b110 ("
b100 #"
b1 c
b1001 ^
b0 Y
b110 T
b100 O
1!
#790
0!
#800
b0 O
b111 T
b1 Y
b1010 ^
b10 c
b0 #"
b111 ("
b1 -"
b1010 2"
b10 7"
1!
#810
0!
#820
b11 7"
b1011 2"
b10 -"
b1000 ("
b1 #"
b11 c
b1011 ^
b10 Y
b1000 T
b1 O
1!
#830
0!
#840
b10 O
b1001 T
b11 Y
b1100 ^
b100 c
b10 #"
b1001 ("
b11 -"
b1100 2"
b100 7"
1!
#850
0!
#860
b101 7"
b1101 2"
b100 -"
b1010 ("
b11 #"
b101 c
b1101 ^
b100 Y
b1010 T
b11 O
1!
#870
0!
#880
b100 O
b0 T
b101 Y
b1110 ^
b110 c
b100 #"
b0 ("
b101 -"
b1110 2"
b110 7"
1!
#890
0!
#900
b111 7"
b0 2"
b110 -"
b1 ("
b0 #"
b111 c
b0 ^
b110 Y
b1 T
b0 O
1!
#910
0!
#920
b1 O
b10 T
b111 Y
b1 ^
b1000 c
b1 #"
b10 ("
b111 -"
b1 2"
b1000 7"
1!
#930
0!
#940
b1001 7"
b10 2"
b1000 -"
b11 ("
b10 #"
b1001 c
b10 ^
b1000 Y
b11 T
b10 O
1!
#950
0!
#960
b11 O
b100 T
b1001 Y
b11 ^
b1010 c
b11 #"
b100 ("
b1001 -"
b11 2"
b1010 7"
1!
#970
0!
#980
b1011 7"
b100 2"
b1010 -"
b101 ("
b100 #"
b1011 c
b100 ^
b1010 Y
b101 T
b100 O
1!
#990
0!
#1000
b0 O
b110 T
b1011 Y
b101 ^
b1100 c
b0 #"
b110 ("
b1011 -"
b101 2"
b1100 7"
1!
#1010
0!
#1020
b1101 7"
b110 2"
b1100 -"
b111 ("
b1 #"
b1101 c
b110 ^
b1100 Y
b111 T
b1 O
1!
#1030
0!
#1040
b10 O
b1000 T
b0 Y
b111 ^
b1110 c
b10 #"
b1000 ("
b0 -"
b111 2"
b1110 7"
1!
#1050
0!
#1060
b1111 7"
b1000 2"
b1 -"
b1001 ("
b11 #"
b1111 c
b1000 ^
b1 Y
b1001 T
b11 O
1!
#1070
0!
#1080
b100 O
b1010 T
b10 Y
b1001 ^
b10000 c
b100 #"
b1010 ("
b10 -"
b1001 2"
b10000 7"
1!
#1090
0!
#1100
b10001 7"
b1010 2"
b11 -"
b0 ("
b0 #"
b10001 c
b1010 ^
b11 Y
b0 T
b0 O
1!
#1110
0!
#1120
b1 O
b1 T
b100 Y
b1011 ^
b10010 c
b1 #"
b1 ("
b100 -"
b1011 2"
b10010 7"
1!
#1130
0!
#1140
b0 7"
b1100 2"
b101 -"
b10 ("
b10 #"
b0 c
b1100 ^
b101 Y
b10 T
b10 O
1!
#1150
0!
#1160
b11 O
b11 T
b110 Y
b1101 ^
b1 c
b11 #"
b11 ("
b110 -"
b1101 2"
b1 7"
1!
#1170
0!
#1180
b10 7"
b1110 2"
b111 -"
b100 ("
b100 #"
b10 c
b1110 ^
b111 Y
b100 T
b100 O
1!
#1190
0!
#1200
b0 O
b101 T
b1000 Y
b0 ^
b11 c
b0 #"
b101 ("
b1000 -"
b0 2"
b11 7"
1!
#1210
0!
#1220
b100 7"
b1 2"
b1001 -"
b110 ("
b1 #"
b100 c
b1 ^
b1001 Y
b110 T
b1 O
1!
#1230
0!
#1240
b10 O
b111 T
b1010 Y
b10 ^
b101 c
b10 #"
b111 ("
b1010 -"
b10 2"
b101 7"
1!
#1250
0!
#1260
b110 7"
b11 2"
b1011 -"
b1000 ("
b11 #"
b110 c
b11 ^
b1011 Y
b1000 T
b11 O
1!
#1270
0!
#1280
b100 O
b1001 T
b1100 Y
b100 ^
b111 c
b100 #"
b1001 ("
b1100 -"
b100 2"
b111 7"
1!
#1290
0!
#1300
b1000 7"
b101 2"
b0 -"
b1010 ("
b0 #"
b1000 c
b101 ^
b0 Y
b1010 T
b0 O
1!
#1310
0!
#1320
b1 O
b0 T
b1 Y
b110 ^
b1001 c
b1 #"
b0 ("
b1 -"
b110 2"
b1001 7"
1!
#1330
0!
#1340
b1010 7"
b111 2"
b10 -"
b1 ("
b10 #"
b1010 c
b111 ^
b10 Y
b1 T
b10 O
1!
#1350
0!
#1360
b11 O
b10 T
b11 Y
b1000 ^
b1011 c
b11 #"
b10 ("
b11 -"
b1000 2"
b1011 7"
1!
#1370
0!
#1380
b1100 7"
b1001 2"
b100 -"
b11 ("
b100 #"
b1100 c
b1001 ^
b100 Y
b11 T
b100 O
1!
#1390
0!
#1400
b0 O
b100 T
b101 Y
b1010 ^
b1101 c
b0 #"
b100 ("
b101 -"
b1010 2"
b1101 7"
1!
#1410
0!
#1420
b1110 7"
b1011 2"
b110 -"
b101 ("
b1 #"
b1110 c
b1011 ^
b110 Y
b101 T
b1 O
1!
#1430
0!
